reduceplus/README.MD
reduceplus/__init__.py
reduceplus/requirements.txt
reduceplus/thirdparty.json
reduceplus-0.10.dist-info/LICENSE.rst
reduceplus-0.10.dist-info/METADATA
reduceplus-0.10.dist-info/WHEEL
reduceplus-0.10.dist-info/top_level.txt
reduceplus-0.10.dist-info/RECORD
