Metadata-Version: 2.1
Name: reduceplus
Version: 0.10
Summary: like functools.reduce but with exception handling, args and kwargs
Home-page: https://github.com/hansalemaos/reduceplus
Author: Johannes Fischer
Author-email: aulasparticularesdealemaosp@gmail.com
License: MIT
Keywords: reduce
Classifier: Development Status :: 4 - Beta
Classifier: Programming Language :: Python :: 3 :: Only
Classifier: Programming Language :: Python :: 3.10
Classifier: Topic :: Software Development :: Libraries :: Python Modules
Classifier: Topic :: Utilities
License-File: LICENSE.rst
